{
    "swagger": "2.0",
    "info": {
        "contact": {},
        "version": "1.0.0",
        "title": "Q-Post user microservice"
    },
    "paths": {
        "/health": {
            "get": {
                "tags": [
                    "Health"
                ],
                "summary": "Service healthcheck",
                "responses": {
                    "200": {
                        "description": "OK"
                    }
                }
            }
        },
        "/users/{id}": {
            "get": {
                "description": "Get user by id",
                "consumes": [
                    "application/json"
                ],
                "produces": [
                    "application/json"
                ],
                "tags": [
                    "Users"
                ],
                "summary": "Get user by id",
                "parameters": [
                    {
                        "type": "string",
                        "description": "user id",
                        "name": "id",
                        "in": "path",
                        "required": true
                    }
                ],
                "responses": {
                    "200": {
                        "description": "OK",
                        "schema": {
                            "type": "string"
                        }
                    },
                    "400": {
                        "description": "Bad Request",
                        "schema": {
                            "type": "object",
                            "additionalProperties": {
                                "type": "string"
                            }
                        }
                    },
                    "500": {
                        "description": "Internal Server Error",
                        "schema": {
                            "type": "object",
                            "additionalProperties": {
                                "type": "string"
                            }
                        }
                    }
                }
            }
        }
    }
}